MANIFEST.in
README.md
setup.py
micropython_sht30.egg-info/PKG-INFO
micropython_sht30.egg-info/SOURCES.txt
micropython_sht30.egg-info/dependency_links.txt
micropython_sht30.egg-info/top_level.txt
sht30/__init__.py
sht30/sht30.py